pclpy/__init__.py
pclpy/__version__.py
pclpy/api.py
pclpy/pcl.cp36-win_amd64.pyd
pclpy/utils.py
pclpy/io/__init__.py
pclpy/io/functions.py
pclpy/io/las.py
pclpy/src/pclpy.cpp
pclpy/src/generated_modules/_2d_loader.cpp
pclpy/src/generated_modules/_base_loader.cpp
pclpy/src/generated_modules/_common_loader.cpp
pclpy/src/generated_modules/_features_loader.cpp
pclpy/src/generated_modules/_filters_loader.cpp
pclpy/src/generated_modules/_geometry_loader.cpp
pclpy/src/generated_modules/_io_loader.cpp
pclpy/src/generated_modules/_kdtree_loader.cpp
pclpy/src/generated_modules/_octree_loader.cpp
pclpy/src/generated_modules/_recognition_loader.cpp
pclpy/src/generated_modules/_sample_consensus_loader.cpp
pclpy/src/generated_modules/_search_loader.cpp
pclpy/src/generated_modules/_segmentation_loader.cpp
pclpy/src/generated_modules/_stereo_loader.cpp
pclpy/src/generated_modules/_surface_loader.cpp
pclpy/src/generated_modules/_tracking_loader.cpp
pclpy/src/generated_modules/_visualization_loader.cpp
pclpy/tests/__init__.py
pclpy/tests/test.py
pclpy/tests/test_eigen.py
pclpy/tests/test_features.py
pclpy/tests/test_filters.py
pclpy/tests/test_io.py
pclpy/tests/test_octree.py
pclpy/tests/test_point_types.py
pclpy/tests/test_sample_consensus.py
pclpy/tests/test_segmentation.py
pclpy/tests/test_surface.py
pclpy/tests/test_visualization.py
pclpy/tests/tests_initialize.py
pclpy/view/__init__.py
pclpy/view/cloudcompare.py
pclpy/view/vtk.py
pclpy-0.11.0.dist-info/METADATA
pclpy-0.11.0.dist-info/RECORD
pclpy-0.11.0.dist-info/WHEEL
pclpy-0.11.0.dist-info/top_level.txt
