Metadata-Version: 2.1
Name: pclpy
Version: 0.11.0
Summary: Python bindings for the Point Cloud Library
Home-page: https://www.github.com/davidcaron/pclpy
Author: David Caron
Author-email: dcaron05@gmail.com
License: MIT
Platform: UNKNOWN
Classifier: License :: OSI Approved :: MIT License
Classifier: Operating System :: Microsoft :: Windows
Classifier: Programming Language :: Python
Classifier: Programming Language :: Python :: 3.6
Classifier: Programming Language :: Python :: Implementation :: CPython
Requires-Python: ==3.6.*
Requires-Dist: laspy
Requires-Dist: numpy
Requires-Dist: pclpy-dependencies (>=0.2.1)
